pincelate/__init__.py
pincelate/cmudictdata.py
pincelate/featurephone.py
pincelate/seq2seq.py
pincelate/train.py
pincelate/models/orth-phon-enc256-dec256-infer-decoder.h5
pincelate/models/orth-phon-enc256-dec256-infer-encoder.h5
pincelate/models/orth-phon-enc256-dec256-obj.pickle
pincelate/models/orth-phon-enc256-dec256-training.h5
pincelate/models/phon-orth-enc256-dec256-infer-decoder.h5
pincelate/models/phon-orth-enc256-dec256-infer-encoder.h5
pincelate/models/phon-orth-enc256-dec256-obj.pickle
pincelate/models/phon-orth-enc256-dec256-training.h5
pincelate-0.0.1.dist-info/LICENSE
pincelate-0.0.1.dist-info/METADATA
pincelate-0.0.1.dist-info/WHEEL
pincelate-0.0.1.dist-info/top_level.txt
pincelate-0.0.1.dist-info/RECORD
