Metadata-Version: 2.1
Name: pincelate
Version: 0.0.1
Summary: Easy to use ML model for spelling and sounding out words
Home-page: https://github.com/aparrish/pincelate
Author: Allison Parrish
Author-email: allison@decontextualize.com
License: MIT
Keywords: pincelate
Platform: UNKNOWN
Classifier: Development Status :: 3 - Alpha
Classifier: License :: OSI Approved :: BSD License
Classifier: Programming Language :: Python :: 3
Classifier: Programming Language :: Python :: 3.6
Classifier: Programming Language :: Python :: 3.7
Classifier: Programming Language :: Python :: 3.8
Classifier: Intended Audience :: Developers
Classifier: Intended Audience :: Education
Classifier: Intended Audience :: Science/Research
Classifier: License :: OSI Approved :: MIT License
Classifier: Natural Language :: English
Classifier: Topic :: Artistic Software
Classifier: Topic :: Scientific/Engineering :: Artificial Intelligence
Requires-Dist: Keras (>=2.2.0)
Requires-Dist: pronouncing (>=0.2.0)
Requires-Dist: scikit-learn (>=0.20.0)
